Metadata-Version: 2.1
Name: msa-cigars
Version: 0.0.1
Summary: To return CIGAR strings of a multiple sequences alignment
Home-page: https://github.com/linzhi2013/
Author: Guanliang Meng
Author-email: mengguanliang@foxmail.com
License: UNKNOWN
Platform: UNKNOWN
Classifier: Development Status :: 3 - Alpha
Classifier: Intended Audience :: Science/Research
Classifier: Topic :: Scientific/Engineering :: Bio-Informatics
Classifier: License :: OSI Approved :: GNU General Public License v3 or later (GPLv3+)
Classifier: Programming Language :: Python :: 3
Classifier: Operating System :: MacOS :: MacOS X
Classifier: Operating System :: Microsoft :: Windows
Classifier: Operating System :: POSIX :: Linux
Requires-Python: >=3
